loot_generator/__init__.py
loot_generator/generators.py
loot_generator/tables.py
lootgenerator-0.2.0.dist-info/DESCRIPTION.rst
lootgenerator-0.2.0.dist-info/METADATA
lootgenerator-0.2.0.dist-info/RECORD
lootgenerator-0.2.0.dist-info/WHEEL
lootgenerator-0.2.0.dist-info/metadata.json
lootgenerator-0.2.0.dist-info/top_level.txt
