Metadata-Version: 2.0
Name: lootgenerator
Version: 0.2.0
Summary: Tabletop RPG loot generator
Home-page: http://github.com/tengro/lootgenerator
Author: Andrew Liashchuk
Author-email: tengro@gmail.com
License: MIT
Keywords: rpg loot
Platform: UNKNOWN
Classifier: Development Status :: 4 - Beta
Classifier: License :: OSI Approved :: MIT License
Classifier: Programming Language :: Python :: 2.7
Classifier: Topic :: Games/Entertainment
Classifier: Topic :: Games/Entertainment :: Board Games
Classifier: Topic :: Games/Entertainment :: Role-Playing
Classifier: Topic :: Utilities
